{
  "project_info": {
    "project_number": "47980364028",
    "project_id": "dozer-15e08",
    "storage_bucket": "dozer-15e08.appspot.com"
  },
  "client": [
    {
      "client_info": {
        "mobilesdk_app_id": "1:47980364028:android:4ed00886ea8af4801c9779",
        "android_client_info": {
          "package_name": "com.example.dozer_mobile"
        }
      },
      "oauth_client": [],
      "api_key": [
        {
          "current_key": "AIzaSyBJLqqa_KXxhdPrXVTYg81DO8Yy7SmAz0U"
        }
      ],
      "services": {
        "appinvite_service": {
          "other_platform_oauth_client": []
        }
      }
    }
  ],
  "configuration_version": "1"
}